nautobot_fsus/__init__.py
nautobot_fsus/api/__init__.py
nautobot_fsus/api/mixins.py
nautobot_fsus/api/serializers/__init__.py
nautobot_fsus/api/serializers/fsu_templates.py
nautobot_fsus/api/serializers/fsu_types.py
nautobot_fsus/api/serializers/fsus.py
nautobot_fsus/api/urls.py
nautobot_fsus/api/views.py
nautobot_fsus/choices.py
nautobot_fsus/filter_extensions.py
nautobot_fsus/filters/__init__.py
nautobot_fsus/filters/fsu_templates.py
nautobot_fsus/filters/fsu_types.py
nautobot_fsus/filters/fsus.py
nautobot_fsus/filters/mixins.py
nautobot_fsus/forms/__init__.py
nautobot_fsus/forms/fsu_templates.py
nautobot_fsus/forms/fsu_types.py
nautobot_fsus/forms/fsus.py
nautobot_fsus/forms/mixins.py
nautobot_fsus/management/__init__.py
nautobot_fsus/management/commands/__init__.py
nautobot_fsus/management/commands/create_fsus_env.py
nautobot_fsus/management/commands/flush_fsus_env.py
nautobot_fsus/migrations/0001_initial.py
nautobot_fsus/migrations/0002_null_statuses.py
nautobot_fsus/migrations/0003_auto_20240816_2107.py
nautobot_fsus/migrations/__init__.py
nautobot_fsus/models/__init__.py
nautobot_fsus/models/fsu_templates.py
nautobot_fsus/models/fsu_types.py
nautobot_fsus/models/fsus.py
nautobot_fsus/models/mixins.py
nautobot_fsus/navigation.py
nautobot_fsus/signals.py
nautobot_fsus/static/nautobot_fsus/docs/404.html
nautobot_fsus/static/nautobot_fsus/docs/admin/compatibility_matrix.html
nautobot_fsus/static/nautobot_fsus/docs/admin/install.html
nautobot_fsus/static/nautobot_fsus/docs/admin/release_notes/index.html
nautobot_fsus/static/nautobot_fsus/docs/admin/release_notes/version_1.0.html
nautobot_fsus/static/nautobot_fsus/docs/admin/release_notes/version_2.0.html
nautobot_fsus/static/nautobot_fsus/docs/admin/release_notes/version_3.0.html
nautobot_fsus/static/nautobot_fsus/docs/admin/uninstall.html
nautobot_fsus/static/nautobot_fsus/docs/admin/upgrade.html
nautobot_fsus/static/nautobot_fsus/docs/assets/_mkdocstrings.css
nautobot_fsus-3.0.2.dist-info/LICENSE
nautobot_fsus-3.0.2.dist-info/METADATA
nautobot_fsus-3.0.2.dist-info/WHEEL
nautobot_fsus-3.0.2.dist-info/RECORD
