Metadata-Version: 2.1
Name: nautobot-fsus
Version: 3.0.2
Summary: Field Serviceable Units for Nautobot
Home-page: https://github.com/NVIDIA/nautobot-app-fsus
License: Apache-2.0
Keywords: nautobot,nautobot-app,nautobot-plugin
Author: Mark Troyer
Author-email: mtroyer@nvidia.com
Maintainer: Mark Troyer
Maintainer-email: mtroyer@nvidia.com
Requires-Python: >=3.10,<3.13
Classifier: License :: OSI Approved :: Apache Software License
Classifier: Programming Language :: Python :: 3
Classifier: Programming Language :: Python :: 3.10
Classifier: Programming Language :: Python :: 3.11
Classifier: Programming Language :: Python :: 3.12
Requires-Dist: nautobot (>=2.3.0,<3.0.0)
Project-URL: Documentation, https://nvidia.github.io/nautobot-app-fsus/index.html
Project-URL: Repository, https://github.com/NVIDIA/nautobot-app-fsus
